{
  "status": "OPTIMAL",
  "total_cost": 540488.8,
  "setup_cost": 145500.0,
  "holding_cost": 394988.8,
  "capacity": {
    "workstation_X_units_per_week": 800,
    "workstation_Y_minutes_per_week": 10000
  },
  "production_schedule": {
    "B1401": {
      "1": 3316.0,
      "2": 3333.0,
      "3": 3333.0,
      "5": 3333.0,
      "6": 3333.0,
      "7": 3333.0,
      "10": 3333.0,
      "11": 3333.0,
      "12": 3333.0,
      "13": 3333.0,
      "16": 3333.0,
      "17": 3333.0,
      "18": 3333.0
    },
    "B2302": {
      "4": 5000.0,
      "8": 4600.0,
      "9": 5000.0,
      "14": 4600.0,
      "15": 5000.0,
      "19": 4084.0,
      "20": 5000.0
    },
    "B3201": {
      "6": 4100.0,
      "11": 4800.0,
      "17": 4800.0,
      "22": 4542.0
    },
    "B4702": {
      "1": 13600.0,
      "2": 15750.0,
      "7": 16800.0,
      "13": 16800.0,
      "18": 15897.0
    },
    "V1501": {
      "6": 3000.0,
      "11": 3200.0,
      "17": 3200.0,
      "22": 3028.0
    },
    "V6302": {
      "6": 2400.0,
      "7": 2250.0,
      "12": 2400.0,
      "18": 2400.0,
      "23": 2271.0
    },
    "E2801": {
      "1": 650.0,
      "8": 800.0,
      "9": 750.0,
      "14": 800.0,
      "20": 800.0,
      "25": 757.0
    }
  },
  "inventory": {
    "B1401": {
      "1": 6400.0,
      "2": 6400.0,
      "3": 6400.0,
      "4": 6400.0,
      "5": 9716.0,
      "6": 1049.0,
      "7": 4382.0,
      "8": 4382.0,
      "9": 7715.0,
      "10": 11048.0,
      "11": 1581.0,
      "12": 1581.0,
      "13": 1581.0,
      "14": 4914.0,
      "15": 8247.0,
      "16": 11580.0,
      "17": 2113.0,
      "18": 2113.0,
      "19": 2113.0,
      "20": 5446.0,
      "21": 8779.0,
      "22": 0.0,
      "23": 0.0,
      "24": 0.0,
      "25": 0.0,
      "26": 0.0,
      "27": 0.0,
      "28": 0.0,
      "29": 0.0,
      "30": 0.0
    },
    "B2302": {
      "1": 4000.0,
      "2": 4000.0,
      "3": 4000.0,
      "4": 4000.0,
      "5": 4000.0,
      "6": 0.0,
      "7": 0.0,
      "8": 0.0,
      "9": 0.0,
      "10": 4600.0,
      "11": 0.0,
      "12": 0.0,
      "13": 0.0,
      "14": 0.0,
      "15": 0.0,
      "16": 4600.0,
      "17": 0.0,
      "18": 0.0,
      "19": 0.0,
      "20": 0.0,
      "21": 4084.0,
      "22": 0.0,
      "23": 0.0,
      "24": 0.0,
      "25": 0.0,
      "26": 0.0,
      "27": 0.0,
      "28": 0.0,
      "29": 0.0,
      "30": 0.0
    },
    "B3201": {
      "1": 5200.0,
      "2": 5200.0,
      "3": 5200.0,
      "4": 5200.0,
      "5": 5200.0,
      "6": 400.0,
      "7": 0.0,
      "8": 0.0,
      "9": 0.0,
      "10": 0.0,
      "11": 0.0,
      "12": 0.0,
      "13": 0.0,
      "14": 0.0,
      "15": 0.0,
      "16": 0.0,
      "17": 0.0,
      "18": 0.0,
      "19": 0.0,
      "20": 0.0,
      "21": 0.0,
      "22": 0.0,
      "23": 0.0,
      "24": 0.0,
      "25": 0.0,
      "26": 0.0,
      "27": 0.0,
      "28": 0.0,
      "29": 0.0,
      "30": 0.0
    },
    "B4702": {
      "1": 3200.0,
      "2": 3200.0,
      "3": 3200.0,
      "4": 3200.0,
      "5": 3200.0,
      "6": 0.0,
      "7": 0.0,
      "8": 0.0,
      "9": 0.0,
      "10": 0.0,
      "11": 0.0,
      "12": 0.0,
      "13": 0.0,
      "14": 0.0,
      "15": 0.0,
      "16": 0.0,
      "17": 0.0,
      "18": 0.0,
      "19": 0.0,
      "20": 0.0,
      "21": 0.0,
      "22": 0.0,
      "23": 0.0,
      "24": 0.0,
      "25": 0.0,
      "26": 0.0,
      "27": 0.0,
      "28": 0.0,
      "29": 0.0,
      "30": 0.0
    },
    "V1501": {
      "1": 3200.0,
      "2": 3200.0,
      "3": 3200.0,
      "4": 3200.0,
      "5": 3200.0,
      "6": 3200.0,
      "7": 3200.0,
      "8": 0.0,
      "9": 0.0,
      "10": 0.0,
      "11": 0.0,
      "12": 0.0,
      "13": 0.0,
      "14": 0.0,
      "15": 0.0,
      "16": 0.0,
      "17": 0.0,
      "18": 0.0,
      "19": 0.0,
      "20": 0.0,
      "21": 0.0,
      "22": 0.0,
      "23": 0.0,
      "24": 0.0,
      "25": 0.0,
      "26": 0.0,
      "27": 0.0,
      "28": 0.0,
      "29": 0.0,
      "30": 0.0
    },
    "V6302": {
      "1": 0.0,
      "2": 0.0,
      "3": 0.0,
      "4": 0.0,
      "5": 0.0,
      "6": 0.0,
      "7": 0.0,
      "8": 0.0,
      "9": 0.0,
      "10": 0.0,
      "11": 0.0,
      "12": 0.0,
      "13": 0.0,
      "14": 0.0,
      "15": 0.0,
      "16": 0.0,
      "17": 0.0,
      "18": 0.0,
      "19": 0.0,
      "20": 0.0,
      "21": 0.0,
      "22": 0.0,
      "23": 0.0,
      "24": 0.0,
      "25": 0.0,
      "26": 0.0,
      "27": 0.0,
      "28": 0.0,
      "29": 0.0,
      "30": 0.0
    },
    "E2801": {
      "1": 1214.0,
      "2": 1720.0,
      "3": 1457.0,
      "4": 1334.0,
      "5": 1163.0,
      "6": 968.0,
      "7": 554.0,
      "8": 407.0,
      "9": 1078.0,
      "10": 1583.0,
      "11": 1375.0,
      "12": 1197.0,
      "13": 1029.0,
      "14": 821.0,
      "15": 1448.0,
      "16": 1280.0,
      "17": 1099.0,
      "18": 911.0,
      "19": 699.0,
      "20": 446.0,
      "21": 1027.0,
      "22": 831.0,
      "23": 605.0,
      "24": 366.0,
      "25": 146.0,
      "26": 704.0,
      "27": 521.0,
      "28": 372.0,
      "29": 205.0,
      "30": 0.0
    }
  },
  "capacity_usage": {
    "1": {
      "X_used_units": 650.0,
      "Y_used_minutes": 9948.0
    },
    "2": {
      "X_used_units": -0.0,
      "Y_used_minutes": 9999.0
    },
    "3": {
      "X_used_units": 0.0,
      "Y_used_minutes": 9999.0
    },
    "4": {
      "X_used_units": 0.0,
      "Y_used_minutes": 10000.0
    },
    "5": {
      "X_used_units": 0.0,
      "Y_used_minutes": 9999.0
    },
    "6": {
      "X_used_units": 0.0,
      "Y_used_minutes": 9999.0
    },
    "7": {
      "X_used_units": 0.0,
      "Y_used_minutes": 9999.0
    },
    "8": {
      "X_used_units": 800.0,
      "Y_used_minutes": 9200.0
    },
    "9": {
      "X_used_units": 750.0,
      "Y_used_minutes": 10000.0
    },
    "10": {
      "X_used_units": 0.0,
      "Y_used_minutes": 9999.0
    },
    "11": {
      "X_used_units": -0.0,
      "Y_used_minutes": 9999.0
    },
    "12": {
      "X_used_units": -0.0,
      "Y_used_minutes": 9999.0
    },
    "13": {
      "X_used_units": -0.0,
      "Y_used_minutes": 9999.0
    },
    "14": {
      "X_used_units": 800.0,
      "Y_used_minutes": 9200.0
    },
    "15": {
      "X_used_units": -0.0,
      "Y_used_minutes": 10000.0
    },
    "16": {
      "X_used_units": -0.0,
      "Y_used_minutes": 9999.0
    },
    "17": {
      "X_used_units": -0.0,
      "Y_used_minutes": 9999.0
    },
    "18": {
      "X_used_units": -0.0,
      "Y_used_minutes": 9999.0
    },
    "19": {
      "X_used_units": -0.0,
      "Y_used_minutes": 8168.0
    },
    "20": {
      "X_used_units": 800.0,
      "Y_used_minutes": 10000.0
    },
    "21": {
      "X_used_units": -0.0,
      "Y_used_minutes": -0.0
    },
    "22": {
      "X_used_units": -0.0,
      "Y_used_minutes": 0.0
    },
    "23": {
      "X_used_units": 0.0,
      "Y_used_minutes": -0.0
    },
    "24": {
      "X_used_units": -0.0,
      "Y_used_minutes": -0.0
    },
    "25": {
      "X_used_units": 757.0,
      "Y_used_minutes": -0.0
    },
    "26": {
      "X_used_units": -0.0,
      "Y_used_minutes": -0.0
    },
    "27": {
      "X_used_units": -0.0,
      "Y_used_minutes": 0.0
    },
    "28": {
      "X_used_units": -0.0,
      "Y_used_minutes": 0.0
    },
    "29": {
      "X_used_units": -0.0,
      "Y_used_minutes": 0.0
    },
    "30": {
      "X_used_units": 0.0,
      "Y_used_minutes": 0.0
    }
  }
}